pupeyes/__init__.py
pupeyes/aoi.py
pupeyes/apps/__init__.py
pupeyes/apps/aoi_drawer.py
pupeyes/apps/fixation_viewer.py
pupeyes/apps/pupil_viewer.py
pupeyes/data/__init__.py
pupeyes/data/eyelink.py
pupeyes/data/tobii_titta.py
pupeyes/defaults.py
pupeyes/external/__init__.py
pupeyes/external/based_noise_blinks_detection.py
pupeyes/external/edfreader.py
pupeyes/plot_utils.py
pupeyes/pupil.py
pupeyes/saccades.py
pupeyes/utils.py
pupeyes-0.3.7.dist-info/LICENSE.md
pupeyes-0.3.7.dist-info/METADATA
pupeyes-0.3.7.dist-info/WHEEL
pupeyes-0.3.7.dist-info/RECORD
