Metadata-Version: 2.3
Name: pupeyes
Version: 0.3.7
Summary: PupEyes: Your Buddy for Pupil Size and Eye Movement Data Analysis
License: GNU General Public License v3.0
Author: Han Zhang
Requires-Python: >=3.10.16,<4.0
Classifier: License :: Other/Proprietary License
Classifier: Programming Language :: Python :: 3
Classifier: Programming Language :: Python :: 3.11
Classifier: Programming Language :: Python :: 3.12
Classifier: Programming Language :: Python :: 3.13
Requires-Dist: dash (>=2.18.2,<3.0.0)
Requires-Dist: dash-bootstrap-components (>=1.7.1,<2.0.0)
Requires-Dist: dill (>=0.3.9,<0.4.0)
Requires-Dist: h5py (>=3.14.0,<4.0.0)
Requires-Dist: intervaltree (>=3.1.0,<4.0.0)
Requires-Dist: ipywidgets (>=8.1.5,<9.0.0)
Requires-Dist: nbformat (>=5.10.4,<6.0.0)
Requires-Dist: opencv-python-headless (>=4.4.0.46,<5.0.0.0)
Requires-Dist: pandas (>=2.2.3,<3.0.0)
Requires-Dist: pillow (>=11.1.0,<12.0.0)
Requires-Dist: scipy (>=1.15.2,<2.0.0)
Requires-Dist: seaborn (>=0.13.2,<0.14.0)
Requires-Dist: tables (>=3.0.0,<4.0.0)
Requires-Dist: tqdm (>=4.67.1,<5.0.0)
